MANIFEST.in
README.txt
setup.cfg
setup.py
docs/HISTORY.txt
docs/INSTALL.txt
docs/LICENSE.GPL
docs/LICENSE.txt
plonetheme/__init__.py
plonetheme.bootstrapModern.egg-info/PKG-INFO
plonetheme.bootstrapModern.egg-info/SOURCES.txt
plonetheme.bootstrapModern.egg-info/dependency_links.txt
plonetheme.bootstrapModern.egg-info/entry_points.txt
plonetheme.bootstrapModern.egg-info/namespace_packages.txt
plonetheme.bootstrapModern.egg-info/not-zip-safe
plonetheme.bootstrapModern.egg-info/paster_plugins.txt
plonetheme.bootstrapModern.egg-info/requires.txt
plonetheme.bootstrapModern.egg-info/top_level.txt
plonetheme/bootstrapModern/__init__.py
plonetheme/bootstrapModern/configure.zcml
plonetheme/bootstrapModern/events.py
plonetheme/bootstrapModern/interfaces.py
plonetheme/bootstrapModern/permissions.py
plonetheme/bootstrapModern/profiles.zcml
plonetheme/bootstrapModern/setuphandlers.py
plonetheme/bootstrapModern/skins.zcml
plonetheme/bootstrapModern/tests.py
plonetheme/bootstrapModern/version.txt
plonetheme/bootstrapModern/browser/.DS_Store
plonetheme/bootstrapModern/browser/__init__.py
plonetheme/bootstrapModern/browser/configure.zcml
plonetheme/bootstrapModern/browser/extendedMailchimp.py
plonetheme/bootstrapModern/browser/interfaces.py
plonetheme/bootstrapModern/browser/views.py
plonetheme/bootstrapModern/browser/alternative_templates/portlet.pt
plonetheme/bootstrapModern/browser/alternative_templates/portlet_mailchimp.pt
plonetheme/bootstrapModern/browser/alternative_templates/portletcollection.pt
plonetheme/bootstrapModern/browser/alternative_templates/sections.pt
plonetheme/bootstrapModern/browser/css/.DS_Store
plonetheme/bootstrapModern/browser/css/ajax-loader.gif
plonetheme/bootstrapModern/browser/css/arr-left.svg
plonetheme/bootstrapModern/browser/css/arr-right.svg
plonetheme/bootstrapModern/browser/css/cross.png
plonetheme/bootstrapModern/browser/css/cross_white.png
plonetheme/bootstrapModern/browser/css/enhancements.css
plonetheme/bootstrapModern/browser/css/logo.png
plonetheme/bootstrapModern/browser/css/logo.svg
plonetheme/bootstrapModern/browser/css/menu.css
plonetheme/bootstrapModern/browser/css/menu.svg
plonetheme/bootstrapModern/browser/css/play.svg
plonetheme/bootstrapModern/browser/css/play1.svg
plonetheme/bootstrapModern/browser/css/theme.css
plonetheme/bootstrapModern/browser/css/bootstrap3/bootstrap.css
plonetheme/bootstrapModern/browser/css/font-awesome/css/font-awesome.css
