Metadata-Version: 1.1
Name: plonetheme.bootstrapModern
Version: 0.50
Summary: An installable theme for Plone 4
Home-page: http://svn.plone.org/svn/collective/
Author: Andre Goncalves
Author-email: andre@intk.com
License: GPL
Keywords: web zope plone theme
Platform: UNKNOWN
Classifier: Framework :: Plone
Classifier: Programming Language :: Python
